Workbook

Sheet Dashboard
A1: [INSIRA O LOGO AQUI] | C1: DASHBOARD FINANCEIRO
C2: Período: March/2026
B5: PAGAMENTOS | D5: RECEBIMENTOS
B6: Total de Pagamentos: | C6: =IFERROR('Controle_Pagamentos.xlsx'!Pagamentos!H57,0) | D6: Total a Receber: | E6: =IFERROR('Controle_Recebimentos.xlsx'!Recebimentos!F57,0)
B7: Pagamentos Realizados: | C7: =IFERROR(SUMIF('Controle_Pagamentos.xlsx'!Pagamentos!J:J,"Pago",'Controle_Pagamentos.xlsx'!Pagamentos!H:H),0) | D7: Total Recebido: | E7: =IFERROR(SUMIF('Controle_Recebimentos.xlsx'!Recebimentos!J:J,"Recebido",'Controle_Recebimentos.xlsx'!Recebimentos!F:F),0)
B8: Pagamentos Pendentes: | C8: =IFERROR(SUMIF('Controle_Pagamentos.xlsx'!Pagamentos!J:J,"Pendente",'Controle_Pagamentos.xlsx'!Pagamentos!H:H),0) | D8: Total Pendente: | E8: =IFERROR(SUMIF('Controle_Recebimentos.xlsx'!Recebimentos!J:J,"Pendente",'Controle_Recebimentos.xlsx'!Recebimentos!F:F),0)
B11: RESUMO GERAL
B12: Fluxo de Caixa (Recebimentos - Pagamentos): | C12: =E6-C6
B13: Saldo Positivo: | C13: =IF(C12>0,C12,0)
B14: Saldo Negativo: | C14: =IF(C12<0,C12,0)
B16: FLUXO DE CAIXA DETALHADO
B17: Recebimentos Esperados: | C17: =IFERROR(SUMIF('Controle_Recebimentos.xlsx'!Recebimentos!J:J,"Pendente",'Controle_Recebimentos.xlsx'!Recebimentos!F:F),0)
B18: Pagamentos Esperados: | C18: =IFERROR(SUMIF('Controle_Pagamentos.xlsx'!Pagamentos!J:J,"Pendente",'Controle_Pagamentos.xlsx'!Pagamentos!H:H),0)
B19: Diferença (Recebimentos - Pagamentos): | C19: =C17-C18
B21: ANÁLISE DE ATRASOS
B22: Recebimentos Atrasados: | C22: =IFERROR(SUMIF('Controle_Recebimentos.xlsx'!Recebimentos!J:J,"Atrasado",'Controle_Recebimentos.xlsx'!Recebimentos!F:F),0)
B23: Quantidade de Recebimentos Atrasados: | C23: =IFERROR(COUNTIF('Controle_Recebimentos.xlsx'!Recebimentos!J:J,"Atrasado"),0)
B25: COMPOSIÇÃO DO FATURAMENTO
B26: Total de Equipamentos: | C26: =IFERROR('Controle_Recebimentos.xlsx'!Recebimentos!G57,0)
B27: Total de Serviços: | C27: =IFERROR('Controle_Recebimentos.xlsx'!Recebimentos!H57,0)
B28: % Equipamentos: | C28: =IF('Controle_Recebimentos.xlsx'!Recebimentos!F57=0,0,C26/'Controle_Recebimentos.xlsx'!Recebimentos!F57)
B29: % Serviços: | C29: =IF('Controle_Recebimentos.xlsx'!Recebimentos!F57=0,0,C27/'Controle_Recebimentos.xlsx'!Recebimentos!F57)
B31: INDICADORES-CHAVE (KPIs)
B32: Taxa de Recebimento: | C32: =IFERROR(SUMIF('Controle_Recebimentos.xlsx'!Recebimentos!J:J,"Recebido",'Controle_Recebimentos.xlsx'!Recebimentos!F:F)/'Controle_Recebimentos.xlsx'!Recebimentos!F57,0)
B33: Ticket Médio de Recebimento: | C33: =IFERROR('Controle_Recebimentos.xlsx'!Recebimentos!F57/COUNTA('Controle_Recebimentos.xlsx'!Recebimentos!B6:B55),0)
B34: Ticket Médio de Pagamento: | C34: =IFERROR('Controle_Pagamentos.xlsx'!Pagamentos!H57/COUNTA('Controle_Pagamentos.xlsx'!Pagamentos!B6:B55),0)
B35: Quantidade Total de Transações: | C35: =COUNTA('Controle_Recebimentos.xlsx'!Recebimentos!B6:B55)+COUNTA('Controle_Pagamentos.xlsx'!Pagamentos!B6:B55)

Sheet Análise Temporal
A1: [INSIRA O LOGO AQUI] | C1: ANÁLISE TEMPORAL
C2: Comparativo de períodos
B5: INSTRUÇÕES DE USO:
B6: 1. Esta aba é para análise de dados históricos
B7: 2. Copie dados de períodos anteriores para comparação
B8: 3. Use as fórmulas abaixo para calcular variações
B10: COMPARATIVO DE PERÍODOS
B11: Métrica | C11: Período Atual | D11: Período Anterior | E11: Variação
B12: Total Recebimentos
B13: Total Pagamentos
B14: Fluxo Líquido
B15: Recebimentos Atrasados

Sheet Guia de Uso
B1: GUIA DE USO - SISTEMA DE CONTROLE FINANCEIRO
B5: COMO USAR ESTA PLANILHA
B7: 1. INSERIR LOGO - Clique na célula com texto '[INSIRA O LOGO AQUI]' em cada aba e insira sua imagem de logo.
B9: 2. PLANILHA DE PAGAMENTOS
B10: - Nome Completo: Digite o nome completo do beneficiário
B11: - CPF: Digite 11 dígitos (validação automática)
B12: - Banco: Selecione da lista suspensa
B13: - Chave Pix: Digite a chave Pix (CPF, email, telefone ou aleatória)
B14: - Tipo de Serviço: Selecione da lista suspensa
B15: - Centro de Custo: Selecione da lista suspensa
B16: - Valor: Digite o valor (deve ser positivo)
B17: - Data Pagamento: Digite a data (não pode ser anterior a hoje)
... B44: SUPORTE - Para dúvidas, consulte os exemplos ou contate o administrador do sistema.
